ngstk
