Metadata-Version: 2.1
Name: ngstk
Version: 0.0.1rc2
Summary: Next-generation sequencing utility functions
Home-page: https://github.com/pepkit/ngstk/
Author: Vince Reuter
License: BSD2
Keywords: bioinformatics,sequencing,ngs
Platform: UNKNOWN
Classifier: Development Status :: 4 - Beta
Classifier: License :: OSI Approved :: BSD License
Classifier: Programming Language :: Python :: 2.7
Classifier: Programming Language :: Python :: 3.5
Classifier: Programming Language :: Python :: 3.6
